cloudshell/__init__.py
cloudshell/networking/__init__.py
cloudshell/networking/cisco/__init__.py
cloudshell/networking/cisco/iosxr/__init__.py
cloudshell/networking/cisco/iosxr/constants.py
cloudshell/networking/cisco/iosxr/cli/__init__.py
cloudshell/networking/cisco/iosxr/cli/command_modes.py
cloudshell/networking/cisco/iosxr/cli/handler.py
cloudshell/networking/cisco/iosxr/command_actions/__init__.py
cloudshell/networking/cisco/iosxr/command_actions/add_remove_vlan.py
cloudshell/networking/cisco/iosxr/command_actions/iface.py
cloudshell/networking/cisco/iosxr/command_actions/system.py
cloudshell/networking/cisco/iosxr/command_templates/__init__.py
cloudshell/networking/cisco/iosxr/command_templates/system.py
cloudshell/networking/cisco/iosxr/flows/__init__.py
cloudshell/networking/cisco/iosxr/flows/configuration.py
cloudshell/networking/cisco/iosxr/flows/connectivity.py
cloudshell/networking/cisco/iosxr/flows/firmware.py
tests/__init__.py
tests/cloudshell/__init__.py
tests/cloudshell/networking/__init__.py
tests/cloudshell/networking/cisco/__init__.py
tests/cloudshell/networking/cisco/iosxr/__init__.py
tests/cloudshell/networking/cisco/iosxr/test_constants.py
cloudshell_networking_cisco_iosxr-5.0.1.dist-info/METADATA
cloudshell_networking_cisco_iosxr-5.0.1.dist-info/WHEEL
cloudshell_networking_cisco_iosxr-5.0.1.dist-info/top_level.txt
cloudshell_networking_cisco_iosxr-5.0.1.dist-info/RECORD
