Metadata-Version: 2.1
Name: cloudshell-networking-cisco-iosxr
Version: 5.0.1
Summary: QualiSystems networking Cisco IOS XR package
Home-page: http://www.qualisystems.com/
Author: QualiSystems
Author-email: info@qualisystems.com
Requires-Python: ~=3.7
Requires-Dist: cloudshell-networking-cisco (<8.0,>=7.0)
Requires-Dist: cloudshell-shell-flows (<3.0,>=2.0)
Requires-Dist: cloudshell-shell-connectivity-flow (<4.0,>=3.1.3)
